foreman_yml/__init__.py
foreman_yml/base.py
foreman_yml/cleanup.py
foreman_yml/dump.py
foreman_yml/helper.py
foreman_yml/importer.py
foreman_yml/log.py
foreman_yml/main.py
foreman_yml/validator.py
foreman_yml/version.py
foreman_yml/voluptuous.py
foreman_yml-1.0.4.dist-info/DESCRIPTION.rst
foreman_yml-1.0.4.dist-info/METADATA
foreman_yml-1.0.4.dist-info/RECORD
foreman_yml-1.0.4.dist-info/WHEEL
foreman_yml-1.0.4.dist-info/entry_points.txt
foreman_yml-1.0.4.dist-info/metadata.json
foreman_yml-1.0.4.dist-info/top_level.txt
