Metadata-Version: 2.0
Name: foreman-yml
Version: 1.0.4
Summary: Foreman YAML client
Home-page: https://github.com/adfinis-sygroup/foreman-yml
Author: Adfinis SyGroup AG
Author-email: info@adfinis-sygroup.ch
License: UNKNOWN
Keywords: foreman,yaml,api
Platform: UNKNOWN
Classifier: Development Status :: 5 - Production/Stable
Classifier: Environment :: Console
Classifier: Intended Audience :: Developers
Classifier: Intended Audience :: System Administrators
Classifier: Intended Audience :: Information Technology
Classifier: License :: OSI Approved :: GNU General Public License v3 (GPLv3)
Classifier: Natural Language :: English
Classifier: Operating System :: OS Independent
Classifier: Programming Language :: Python :: 2.6
Classifier: Topic :: System :: Systems Administration
Requires-Dist: python-foreman
Requires-Dist: pyyaml
Requires-Dist: requests
